nonebot_plugin_send_message/__init__.py
nonebot_plugin_send_message/config.py
nonebot_plugin_send_message-3.2.dist-info/METADATA
nonebot_plugin_send_message-3.2.dist-info/WHEEL
nonebot_plugin_send_message-3.2.dist-info/top_level.txt
nonebot_plugin_send_message-3.2.dist-info/RECORD
