Metadata-Version: 2.1
Name: nonebot-plugin-send-message
Version: 3.2
Summary: 一个支持双向聊天的传话插件，可用于临时聊天而不想加好友场景
Home-page: https://github.com/bingqiu456/nonebot_plugin_send_message
Author: bingyue
Author-email: hello-yiqiu@qq.com
Keywords: nonebot_plugin_send_message,nonebot,nonebot_plugin
Requires-Dist: nonebot2 (>=2.0.0rc3)
Requires-Dist: nonebot-adapter-onebot (>=2.2.1)
